tklearn/__init__.py
tklearn/configs.py
tklearn/dataset.py
tklearn/utils.py
tklearn/embedding/__init__.py
tklearn/embedding/bert.py
tklearn/embedding/conceptnet.py
tklearn/embedding/loader.py
tklearn/feature_extraction/__init__.py
tklearn/feature_extraction/text/__init__.py
tklearn/feature_extraction/text/embedding.py
tklearn/feature_extraction/text/hatebase.py
tklearn/matrices/__init__.py
tklearn/matrices/scorer.py
tklearn/model_selection/__init__.py
tklearn/model_selection/_validation.py
tklearn/preprocessing/__init__.py
tklearn/preprocessing/text.py
tklearn/preprocessing/tweet.py
tklearn-0.0.4.dist-info/LICENSE
tklearn-0.0.4.dist-info/METADATA
tklearn-0.0.4.dist-info/WHEEL
tklearn-0.0.4.dist-info/top_level.txt
tklearn-0.0.4.dist-info/RECORD
