Metadata-Version: 2.1
Name: tklearn
Version: 0.0.4
Summary: Helps computers to understand human languages.
Home-page: https://github.com/ysenarath/textkit-learn
Author: Yasas Senarath
License: UNKNOWN
Platform: UNKNOWN
Classifier: Programming Language :: Python :: 3
Classifier: Operating System :: OS Independent
Requires-Python: >=3.6
